verilog/design.v
module atm_module (
    input wire clk,
    input wire rst_n,
    input wire card_inserted,
    input wire [15:0] pin_input,
    input wire balance_req,
    input wire withdrawal_req,
    input wire deposit_req,
    input wire pin_change_req,
    input wire transaction_done,
    input wire [15:0] amount,
    input wire [7:0] card_number_input,
    output reg [7:0] current_state,
    output reg [15:0] balance,
    output reg transaction_success,
    output reg [7:0] error_code
);

    // State Parameters
    parameter IDLE = 8'b0000_0000;
    parameter CARD_INSERT = 8'b0000_0001;
    parameter CARD_VALIDATE = 8'b0000_0010;
    parameter CARD_ERROR = 8'b0000_0011;
    parameter CARD_VALID = 8'b0000_0100;
    parameter PIN_ENTRY = 8'b0000_0101;
    parameter PIN_CHECK = 8'b0000_0110;
    parameter PIN_ERROR = 8'b0000_0111;
    parameter PIN_VALID = 8'b0000_1000;
    parameter MENU = 8'b0000_1001;
    parameter BALANCE_ENQ = 8'b0001_0000;
    parameter WITHDRAWAL = 8'b0001_0001;
    parameter DEPOSIT = 8'b0001_0010;
    parameter PIN_CHANGE = 8'b0001_0011;
    parameter AMOUNT_VALID = 8'b0001_0100;
    parameter PRINT_RECEIPT = 8'b0001_0101;

    // Error Codes
    parameter NO_ERROR = 8'h00;
    parameter INVALID_CARD = 8'h01;
    parameter INVALID_PIN = 8'h02;
    parameter INSUF_BALANCE = 8'h03;
    parameter LIMIT_EXCEED = 8'h04;

    // Internal Registers
    reg [7:0] next_state;
    reg [7:0] current_card_number;
    reg [15:0] stored_pin;
    reg [15:0] daily_limit;
    reg [2:0] pin_attempts;
    reg pin_valid;

    // Memory Arrays
    reg [15:0] card_data [0:35];

    // Card Data Structure Indices
    parameter CARD_PIN_IDX = 0;
    parameter CARD_BALANCE_IDX = 1;
    parameter CARD_STATUS_IDX = 2;
    parameter CARD_LIMIT_IDX = 3;

    integer output_file;
    
    initial begin
        $readmemh("atm_data_g31.hex", card_data);
        output_file = $fopen("output_data.txt", "w");
        if (output_file == 0) begin
            $display("Error: Could not open output_data.hex");
            $finish;
        end
    end

    // Combined Sequential and State Transition Logic
    always @(posedge clk or negedge rst_n) begin
        if (!rst_n) begin
            current_state <= IDLE;
            error_code <= NO_ERROR;
            transaction_success <= 0;
            pin_attempts <= 0;
            balance <= 16'h0000;
            current_card_number <= 8'h00;
            stored_pin <= 16'h0000;
            daily_limit <= 16'h0000;
            pin_valid <= 0;
            next_state <= IDLE;
        end else begin
            current_state <= next_state;
            
            case (current_state)
                IDLE: begin
                    if (card_inserted)
                        next_state <= CARD_INSERT;
                end

                CARD_INSERT: begin
                    current_card_number <= card_number_input;
                    error_code <= NO_ERROR;
                    transaction_success <= 0;
                    pin_attempts <= 0;
                    next_state <= CARD_VALIDATE;
                end

                CARD_VALIDATE: begin
                    if (card_data[current_card_number*4 + CARD_STATUS_IDX] != 16'h0001) begin
                        error_code <= INVALID_CARD;
                        next_state <= CARD_ERROR;
                    end else begin
                        stored_pin <= card_data[current_card_number*4 + CARD_PIN_IDX];
                        daily_limit <= card_data[current_card_number*4 + CARD_LIMIT_IDX];
                        error_code <= NO_ERROR;
                        next_state <= CARD_VALID;
                    end
                end

                CARD_ERROR: begin
                    if (!card_inserted)
                        next_state <= IDLE;
                end

                CARD_VALID: begin
                    next_state <= PIN_ENTRY;
                end

                PIN_ENTRY: begin
                    next_state <= PIN_CHECK;
                end

                PIN_CHECK: begin
                    if (pin_input == stored_pin) begin
                        next_state <= MENU;
                        pin_valid <= 1;
                    end else begin
                        pin_attempts <= pin_attempts + 1;
                        if (pin_attempts >= 2) begin
                            next_state <= CARD_ERROR;
                        end else begin
                            next_state <= PIN_ERROR;
                        end
                    end
                end

                PIN_ERROR: begin
                    next_state <= PIN_ENTRY;
                end

                MENU: begin
                    if (!card_inserted)
                        next_state <= IDLE;
                    else if (balance_req)
                        next_state <= BALANCE_ENQ;
                    else if (withdrawal_req)
                        next_state <= WITHDRAWAL;
                    else if (deposit_req)
                        next_state <= DEPOSIT;
                    else if (pin_change_req)
                        next_state <= PIN_CHANGE;
                end

                BALANCE_ENQ: begin
                    balance <= card_data[current_card_number*4 + CARD_BALANCE_IDX];
                    if (transaction_done) begin
                        transaction_success <= 1;
                        next_state <= PRINT_RECEIPT;
                    end
                end

                WITHDRAWAL: begin
                    if (amount <= card_data[current_card_number*4 + CARD_BALANCE_IDX] &&
                        amount <= daily_limit) begin
                        if (transaction_done) begin
                            balance <= card_data[current_card_number*4 + CARD_BALANCE_IDX] - amount;
                            card_data[current_card_number*4 + CARD_BALANCE_IDX] <= 
                                card_data[current_card_number*4 + CARD_BALANCE_IDX] - amount;
                            transaction_success <= 1;
                            error_code <= NO_ERROR;
                            next_state <= AMOUNT_VALID;
                        end
                    end else begin
                        if (amount > daily_limit)
                            error_code <= LIMIT_EXCEED;
                        else
                            error_code <= INSUF_BALANCE;
                        next_state <= MENU;
                    end
                end

                DEPOSIT: begin
                    if (transaction_done) begin
                        balance <= card_data[current_card_number*4 + CARD_BALANCE_IDX] + amount;
                        card_data[current_card_number*4 + CARD_BALANCE_IDX] <= 
                            card_data[current_card_number*4 + CARD_BALANCE_IDX] + amount;
                        transaction_success <= 1;
                        error_code <= NO_ERROR;
                        next_state <= AMOUNT_VALID;
                    end
                end

                PIN_CHANGE: begin
                    if (!card_inserted)
                        next_state <= IDLE;
                    else if (transaction_done)
                        next_state <= MENU;
                end

                AMOUNT_VALID: begin
                    if (!card_inserted)
                        next_state <= IDLE;
                    else if (transaction_done)
                        next_state <= PRINT_RECEIPT;
                end

                PRINT_RECEIPT: begin
                    if (!card_inserted)
                        next_state <= IDLE;
                    else
                        next_state <= MENU;
                    $fwrite(output_file, "%b\n", balance);
                    $fwrite(output_file, "%b\n", error_code);
                end

                default: next_state <= IDLE;
            endcase
        end
    end
endmodule

verilog/atm_module_testbench.v
`include "design.v"

module tb_atm_module;
    reg clk;
    reg rst_n;
    reg card_inserted;
    reg [15:0] pin_input;
    reg balance_req;
    reg withdrawal_req;
    reg deposit_req;
    reg pin_change_req;
    reg transaction_done;
    reg [15:0] amount;
    reg [7:0] card_number_input;

    wire [7:0] current_state;
    wire [15:0] balance;
    wire transaction_success;
    wire [7:0] error_code;

    // Register to store the transaction type
    reg [8*16-1:0] transaction_type; // 16 characters × 8 bits per character

    // Instantiate the ATM module
    atm_module uut (
        .clk(clk),
        .rst_n(rst_n),
        .card_inserted(card_inserted),
        .pin_input(pin_input),
        .balance_req(balance_req),
        .withdrawal_req(withdrawal_req),
        .deposit_req(deposit_req),
        .pin_change_req(pin_change_req),
        .transaction_done(transaction_done),
        .amount(amount),
        .card_number_input(card_number_input),
        .current_state(current_state),
        .balance(balance),
        .transaction_success(transaction_success),
        .error_code(error_code)
    );

    // Clock generation
    initial begin
        clk = 0;
        forever #5 clk = ~clk; // 10 ns clock period
    end

    // Transaction type logic
    always @(*) begin
        if (balance_req)
            transaction_type = "Balance Inquiry";
        else if (withdrawal_req)
            transaction_type = "Withdrawal";
        else if (deposit_req)
            transaction_type = "Deposit";
        else if (pin_change_req)
            transaction_type = "PIN Change";
        else
            transaction_type = "None";
    end

    // Test sequence
    initial begin
        // Reset the system
        rst_n = 0;
        card_inserted = 0;
        pin_input = 16'h0000;
        balance_req = 0;
        withdrawal_req = 0;
        deposit_req = 0;
        pin_change_req = 0;
        transaction_done = 0;
        amount = 16'h0000;
        card_number_input = 8'h00;

        #20 rst_n = 1;

        // Test case 1: Valid card and PIN, balance inquiry
        #20;
        card_number_input = 8'h00;
        card_inserted = 1;
        #20;
        pin_input = 16'h1234;
        #40;
        balance_req = 1;
        #20 balance_req = 0;
        #20 transaction_done = 1;
        #20 transaction_done = 0;

        // Test case 2: Valid card, invalid PIN (multiple attempts)
        #40;
        card_number_input = 8'h01;
        card_inserted = 1;
        #20;
        pin_input = 16'h1111;  // Incorrect PIN
        #40;
        pin_input = 16'h2222;  // Incorrect PIN
        #40;
        pin_input = 16'h3333;  // Incorrect PIN, triggers card lock

        // Test case 3: Withdrawal exceeding balance
        #40;
        card_number_input = 8'h00;
        pin_input = 16'h1234;
        #40;
        withdrawal_req = 1;
        amount = 16'hFFFF;  // Large withdrawal amount
        #20 withdrawal_req = 0;
        #20 transaction_done = 1;
        #20 transaction_done = 0;

        // Test case 4: Successful withdrawal
        #40;
        withdrawal_req = 1;
        amount = 16'h0050;  // Valid withdrawal amount
        #20 withdrawal_req = 0;
        #20 transaction_done = 1;
        #20 transaction_done = 0;

        // Test case 5: Deposit operation
        #40;
        deposit_req = 1;
        amount = 16'h0100;  // Deposit amount
        #20 deposit_req = 0;
        #20 transaction_done = 1;
        #20 transaction_done = 0;

        // Test case 6: PIN change
        #40;
        pin_change_req = 1;
        pin_input = 16'h5678;  // New PIN
        #20 pin_change_req = 0;
        #20 transaction_done = 1;
        #20 transaction_done = 0;

        // Test case 7: Invalid card
        #40;
        card_number_input = 8'hFF;  // Nonexistent card
        card_inserted = 1;
        #40;

        // Test case 8: Card removed during operation
        #40;
        card_number_input = 8'h00;
        card_inserted = 1;
        #20;
        pin_input = 16'h1234;
        #40;
        card_inserted = 0;  // Simulate card removal
        #40;

        // Finish simulation
        #100 $finish;
    end

    // Monitor to display simulation details
    initial begin
        $monitor("Time=%0t State=%h Card=%h Pin=%h Error=%h Balance=%h Success=%b Transaction=%s",
                 $time, current_state, card_number_input, pin_input, error_code,
                 balance, transaction_success, transaction_type);
                 
        $dumpfile("atm_test.vcd");
        $dumpvars(0, tb_atm_module);
    end
endmodule

verilog/atm_test.vcd
$date
	Fri Nov 22 09:38:41 2024
$end
$version
	Icarus Verilog
$end
$timescale
	1s
$end
$scope module tb_atm_module $end
$var wire 1 ! transaction_success $end
$var wire 8 " error_code [7:0] $end
$var wire 8 # current_state [7:0] $end
$var wire 16 $ balance [15:0] $end
$var reg 16 % amount [15:0] $end
$var reg 1 & balance_req $end
$var reg 1 ' card_inserted $end
$var reg 8 ( card_number_input [7:0] $end
$var reg 1 ) clk $end
$var reg 1 * deposit_req $end
$var reg 1 + pin_change_req $end
$var reg 16 , pin_input [15:0] $end
$var reg 1 - rst_n $end
$var reg 1 . transaction_done $end
$var reg 128 / transaction_type [127:0] $end
$var reg 1 0 withdrawal_req $end
$scope module uut $end
$var wire 16 1 amount [15:0] $end
$var wire 1 & balance_req $end
$var wire 1 ' card_inserted $end
$var wire 8 2 card_number_input [7:0] $end
$var wire 1 ) clk $end
$var wire 1 * deposit_req $end
$var wire 1 + pin_change_req $end
$var wire 16 3 pin_input [15:0] $end
$var wire 1 - rst_n $end
$var wire 1 . transaction_done $end
$var wire 1 0 withdrawal_req $end
$var parameter 8 4 AMOUNT_VALID $end
$var parameter 8 5 BALANCE_ENQ $end
$var parameter 32 6 CARD_BALANCE_IDX $end
$var parameter 8 7 CARD_ERROR $end
$var parameter 8 8 CARD_INSERT $end
$var parameter 32 9 CARD_LIMIT_IDX $end
$var parameter 32 : CARD_PIN_IDX $end
$var parameter 32 ; CARD_STATUS_IDX $end
$var parameter 8 < CARD_VALID $end
$var parameter 8 = CARD_VALIDATE $end
$var parameter 8 > DEPOSIT $end
$var parameter 8 ? IDLE $end
$var parameter 8 @ INSUF_BALANCE $end
$var parameter 8 A INVALID_CARD $end
$var parameter 8 B INVALID_PIN $end
$var parameter 8 C LIMIT_EXCEED $end
$var parameter 8 D MENU $end
$var parameter 8 E NO_ERROR $end
$var parameter 8 F PIN_CHANGE $end
$var parameter 8 G PIN_CHECK $end
$var parameter 8 H PIN_ENTRY $end
$var parameter 8 I PIN_ERROR $end
$var parameter 8 J PIN_VALID $end
$var parameter 8 K PRINT_RECEIPT $end
$var parameter 8 L WITHDRAWAL $end
$var reg 16 M balance [15:0] $end
$var reg 8 N current_card_number [7:0] $end
$var reg 8 O current_state [7:0] $end
$var reg 16 P daily_limit [15:0] $end
$var reg 8 Q error_code [7:0] $end
$var reg 8 R next_state [7:0] $end
$var reg 3 S pin_attempts [2:0] $end
$var reg 1 T pin_valid $end
$var reg 16 U stored_pin [15:0] $end
$var reg 1 ! transaction_success $end
$var integer 32 V output_file [31:0] $end
$upscope $end
$upscope $end
$enddefinitions $end
$comment Show the parameter values. $end
$dumpall
b10001 L
b10101 K
b1000 J
b111 I
b101 H
b110 G
b10011 F
b0 E
b1001 D
b100 C
b10 B
b1 A
b11 @
b0 ?
b10010 >
b10 =
b100 <
b10 ;
b0 :
b11 9
b1 8
b11 7
b1 6
b10000 5
b10100 4
$end
#0
$dumpvars
b10000000000000000000000000000011 V
b0 U
0T
b0 S
b0 R
b0 Q
b0 P
b0 O
b0 N
b0 M
b0 3
b0 2
b0 1
00
b1001110011011110110111001100101 /
0.
0-
b0 ,
0+
0*
0)
b0 (
0'
0&
b0 %
b0 $
b0 #
b0 "
0!
$end
#5
1)
#10
0)
#15
1)
#20
0)
1-
#25
1)
#30
0)
#35
1)
#40
0)
1'
#45
b1 R
1)
#50
0)
#55
b1 #
b1 O
1)
#60
0)
b1001000110100 ,
b1001000110100 3
#65
b10 R
1)
#70
0)
#75
b10 #
b10 O
1)
#80
0)
#85
b100 R
b10100000000 P
b1001000110100 U
1)
#90
0)
#95
b100 #
b100 O
1)
#100
b10000100110000101101100011000010110111001100011011001010010000001001001011011100111000101110101011010010111001001111001 /
0)
1&
#105
b101 R
1)
#110
0)
#115
b101 #
b101 O
1)
#120
b1001110011011110110111001100101 /
0)
0&
#125
b110 R
1)
#130
0)
#135
b110 #
b110 O
1)
#140
0)
1.
#145
1T
b1001 R
1)
#150
0)
#155
b1001 #
b1001 O
1)
#160
0)
0.
#165
1)
#170
0)
#175
1)
#180
0)
#185
1)
#190
0)
#195
1)
#200
0)
b1 (
b1 2
#205
1)
#210
0)
#215
1)
#220
0)
b1000100010001 ,
b1000100010001 3
#225
1)
#230
0)
#235
1)
#240
0)
#245
1)
#250
0)
#255
1)
#260
0)
b10001000100010 ,
b10001000100010 3
#265
1)
#270
0)
#275
1)
#280
0)
#285
1)
#290
0)
#295
1)
#300
0)
b11001100110011 ,
b11001100110011 3
#305
1)
#310
0)
#315
1)
#320
0)
#325
1)
#330
0)
#335
1)
#340
0)
b1001000110100 ,
b1001000110100 3
b0 (
b0 2
#345
1)
#350
0)
#355
1)
#360
0)
#365
1)
#370
0)
#375
1)
#380
b1010111011010010111010001101000011001000111001001100001011101110110000101101100 /
0)
b1111111111111111 %
b1111111111111111 1
10
#385
b10001 R
1)
#390
0)
#395
b10001 #
b10001 O
1)
#400
b1001110011011110110111001100101 /
0)
00
#405
b1001 R
b100 "
b100 Q
1)
#410
0)
#415
b1001 #
b1001 O
1)
#420
0)
1.
#425
1)
#430
0)
#435
1)
#440
0)
0.
#445
1)
#450
0)
#455
1)
#460
0)
#465
1)
#470
0)
#475
1)
#480
b1010111011010010111010001101000011001000111001001100001011101110110000101101100 /
0)
b1010000 %
b1010000 1
10
#485
b10001 R
1)
#490
0)
#495
b10001 #
b10001 O
1)
#500
b1001110011011110110111001100101 /
0)
00
#505
1)
#510
0)
#515
1)
#520
0)
1.
#525
b10100 R
b0 "
b0 Q
1!
b1010000001100000 $
b1010000001100000 M
1)
#530
0)
#535
b1010000000010000 $
b1010000000010000 M
b10100 #
b10100 O
1)
#540
0)
0.
#545
1)
#550
0)
#555
1)
#560
0)
#565
1)
#570
0)
#575
1)
#580
b1000100011001010111000001101111011100110110100101110100 /
0)
b100000000 %
b100000000 1
1*
#585
1)
#590
0)
#595
1)
#600
b1001110011011110110111001100101 /
0)
0*
#605
1)
#610
0)
#615
1)
#620
0)
1.
#625
b10101 R
1)
#630
0)
#635
b10101 #
b10101 O
1)
#640
0)
0.
#645
b1001 R
1)
#650
0)
#655
b1001 #
b1001 O
1)
#660
0)
#665
1)
#670
0)
#675
1)
#680
b1010000010010010100111000100000010000110110100001100001011011100110011101100101 /
0)
b101011001111000 ,
b101011001111000 3
1+
#685
b10011 R
1)
#690
0)
#695
b10011 #
b10011 O
1)
#700
b1001110011011110110111001100101 /
0)
0+
#705
1)
#710
0)
#715
1)
#720
0)
1.
#725
b1001 R
1)
#730
0)
#735
b1001 #
b1001 O
1)
#740
0)
0.
#745
1)
#750
0)
#755
1)
#760
0)
#765
1)
#770
0)
#775
1)
#780
0)
b11111111 (
b11111111 2
#785
1)
#790
0)
#795
1)
#800
0)
#805
1)
#810
0)
#815
1)
#820
0)
#825
1)
#830
0)
#835
1)
#840
0)
#845
1)
#850
0)
#855
1)
#860
0)
b0 (
b0 2
#865
1)
#870
0)
#875
1)
#880
0)
b1001000110100 ,
b1001000110100 3
#885
1)
#890
0)
#895
1)
#900
0)
#905
1)
#910
0)
#915
1)
#920
0)
0'
#925
b0 R
1)
#930
0)
#935
b0 #
b0 O
1)
