verilog/design.sv
module atm_module (
    input wire clk,
    input wire rst_n,
    input wire card_inserted,
    input wire [15:0] pin_input,
    input wire balance_req,
    input wire withdrawal_req,
    input wire deposit_req,
    input wire pin_change_req,
    input wire transaction_done,
    input wire [15:0] amount,
    input wire [7:0] card_number_input,
    output reg [7:0] current_state,
    output reg [15:0] balance,
    output reg transaction_success,
    output reg [7:0] error_code
);

    // State Parameters
    parameter IDLE = 8'b0000_0000;
    parameter CARD_INSERT = 8'b0000_0001;
    parameter CARD_VALIDATE = 8'b0000_0010;
    parameter CARD_ERROR = 8'b0000_0011;
    parameter CARD_VALID = 8'b0000_0100;
    parameter PIN_ENTRY = 8'b0000_0101;
    parameter PIN_CHECK = 8'b0000_0110;
    parameter PIN_ERROR = 8'b0000_0111;
    parameter PIN_VALID = 8'b0000_1000;
    parameter MENU = 8'b0000_1001;
    parameter BALANCE_ENQ   = 8'b0001_0000; 
    parameter WITHDRAWAL    = 8'b0001_0001;
    parameter DEPOSIT       = 8'b0001_0010;
    parameter PIN_CHANGE    = 8'b0001_0011;
    parameter AMOUNT_VALID  = 8'b0001_0100;
    parameter PRINT_RECEIPT = 8'b0001_0101;

    // Error Codes
    parameter NO_ERROR = 8'h00;
    parameter INVALID_CARD = 8'h01;
    parameter INVALID_PIN = 8'h02;
    parameter INSUF_BALANCE = 8'h03;
    parameter LIMIT_EXCEED = 8'h04;

    // Internal Registers
    reg [7:0] next_state;
    reg [7:0] current_card_number;
    reg [15:0] stored_pin;
    reg [15:0] daily_limit;
    reg [2:0] pin_attempts;
    reg pin_valid;

    // Memory Arrays
    reg [15:0] card_data [0:35];

    // Card Data Structure Indices
    parameter CARD_PIN_IDX = 0;
    parameter CARD_BALANCE_IDX = 1;
    parameter CARD_STATUS_IDX = 2;
    parameter CARD_LIMIT_IDX = 3;

    // Initialize memory
    initial begin
        $readmemh("atm_data_g31.hex", card_data);
    end

    // Modified Sequential Logic Block
    always @(posedge clk or negedge rst_n) begin
        if (!rst_n) begin
            current_state <= IDLE;
            error_code <= NO_ERROR;
            transaction_success <= 0;
            pin_attempts <= 0;
            balance <= 16'h0000;
            current_card_number <= 8'h00;
            stored_pin <= 16'h0000;
            daily_limit <= 16'h0000;
            pin_valid <= 0;
        end else begin
            current_state <= next_state;
            
            case (current_state)
                CARD_INSERT: begin
                    current_card_number <= card_number_input;
                    error_code <= NO_ERROR;
                    transaction_success <= 0;
                    pin_attempts <= 0; // Reset attempts on new card
                end

                CARD_VALIDATE: begin
                    if (card_data[current_card_number*4 + CARD_STATUS_IDX] != 16'h0001) begin
                        error_code <= INVALID_CARD;
                    end else begin
                        stored_pin <= card_data[current_card_number*4 + CARD_PIN_IDX];
                        daily_limit <= card_data[current_card_number*4 + CARD_LIMIT_IDX];
                        error_code <= NO_ERROR;
                    end
                end

                PIN_CHECK: begin
                    if (pin_input == stored_pin) begin
                        next_state = PIN_VALID; // Go to new intermediate state
                    end else if (pin_attempts >= 2) begin
                        next_state = CARD_ERROR;
                    end else begin
                        next_state = PIN_ERROR;
                    end
                end
                
                PIN_VALID: begin // New state handler
                    next_state = MENU;
                end
                
                MENU: begin
                    if (!card_inserted) // Add exit condition
                        next_state = IDLE;
                    else if (balance_req)
                        next_state = BALANCE_ENQ;
                    else if (withdrawal_req)
                        next_state = WITHDRAWAL;
                    else if (deposit_req)
                        next_state = DEPOSIT;
                    else if (pin_change_req)
                        next_state = PIN_CHANGE;
                end
                
                BALANCE_ENQ: begin
                    // Fix: Read balance using proper array indexing
                    balance <= card_data[current_card_number*4 + CARD_BALANCE_IDX];
                    if (transaction_done) begin
                        transaction_success <= 1;
                    end
                end

                WITHDRAWAL: begin
                    if (amount <= card_data[current_card_number*4 + CARD_BALANCE_IDX] &&
                        amount <= daily_limit) begin
                        if (transaction_done) begin
                            // Fix: Update balance first, then update card data
                            balance <= card_data[current_card_number*4 + CARD_BALANCE_IDX] - amount;
                            card_data[current_card_number*4 + CARD_BALANCE_IDX] <= 
                                card_data[current_card_number*4 + CARD_BALANCE_IDX] - amount;
                            transaction_success <= 1;
                            error_code <= NO_ERROR;
                        end
                    end else if (amount > daily_limit) begin
                        error_code <= LIMIT_EXCEED;
                    end else begin
                        error_code <= INSUF_BALANCE;
                    end
                end

                DEPOSIT: begin
                    if (transaction_done) begin
                        // Fix: Update balance first, then update card data
                        balance <= card_data[current_card_number*4 + CARD_BALANCE_IDX] + amount;
                        card_data[current_card_number*4 + CARD_BALANCE_IDX] <= 
                            card_data[current_card_number*4 + CARD_BALANCE_IDX] + amount;
                        transaction_success <= 1;
                        error_code <= NO_ERROR;
                    end
                end
                                
                PIN_CHANGE: begin
                    if (!card_inserted)
                        next_state = IDLE;
                    else if (transaction_done)
                        next_state = MENU;
                end
                
                AMOUNT_VALID: begin
                    if (!card_inserted)
                        next_state = IDLE;
                    else if (transaction_done)
                        next_state = PRINT_RECEIPT;
                end
                
                PRINT_RECEIPT: begin
                    if (!card_inserted)
                        next_state = IDLE;
                    else
                        next_state = MENU;
                end
                
                default: next_state = IDLE;
            endcase
        end
    end

    // Modified Combinational Logic Block - Key Changes
    always @(*) begin
        next_state = current_state;

        case (current_state)
            IDLE: begin
                if (card_inserted)
                    next_state = CARD_INSERT;
            end

            CARD_INSERT: begin
                next_state = CARD_VALIDATE;
            end

            CARD_VALIDATE: begin
                if (card_data[current_card_number][CARD_STATUS_IDX] == 16'h0001)
                    next_state = CARD_VALID;
                else
                    next_state = CARD_ERROR;
            end

            CARD_ERROR: begin
                if (!card_inserted)
                    next_state = IDLE;
            end

            CARD_VALID: begin
                next_state = PIN_ENTRY;
            end

            PIN_ENTRY: begin
                next_state = PIN_CHECK;
            end

            PIN_CHECK: begin
                if (pin_input == stored_pin) begin
                    next_state = MENU;
                    pin_valid = 1;
                end else if (pin_attempts >= 2) begin // Check for 2 since increment happens after
                    next_state = CARD_ERROR;
                end else begin
                    next_state = PIN_ERROR;
                end
            end

            PIN_ERROR: begin
                next_state = PIN_ENTRY;
            end

            MENU: begin
                if (balance_req)
                    next_state = BALANCE_ENQ;
                else if (withdrawal_req)
                    next_state = WITHDRAWAL;
                else if (deposit_req)
                    next_state = DEPOSIT;
                else if (pin_change_req)
                    next_state = PIN_CHANGE;
            end

            BALANCE_ENQ: begin
                if (transaction_done)
                    next_state = PRINT_RECEIPT;
            end

            WITHDRAWAL: begin
                if (amount <= card_data[current_card_number][CARD_BALANCE_IDX] &&
                    amount <= daily_limit) begin
                    if (transaction_done)
                        next_state = AMOUNT_VALID;
                end else
                    next_state = MENU;
            end

            DEPOSIT: begin
                if (transaction_done)
                    next_state = AMOUNT_VALID;
            end

            PIN_CHANGE: begin
                if (transaction_done)
                    next_state = MENU;
            end

            AMOUNT_VALID: begin
                if (transaction_done)
                    next_state = PRINT_RECEIPT;
            end

            PRINT_RECEIPT: begin
                next_state = MENU;
            end

            default: next_state = IDLE;
        endcase
    end
endmodule

verilog/atm_module_testbench.sv
module tb_atm_module;
    // Inputs
    reg clk;
    reg rst_n;
    reg card_inserted;
    reg [15:0] pin_input;
    reg balance_req;
    reg withdrawal_req;
    reg deposit_req;
    reg pin_change_req;
    reg transaction_done;
    reg [15:0] amount;
    reg [7:0] card_number_input;

    // Outputs
    wire [7:0] current_state;
    wire [15:0] balance;
    wire transaction_success;
    wire [7:0] error_code;

    // Instantiate ATM module
    atm_module uut (
        .clk(clk),
        .rst_n(rst_n),
        .card_inserted(card_inserted),
        .pin_input(pin_input),
        .balance_req(balance_req),
        .withdrawal_req(withdrawal_req),
        .deposit_req(deposit_req),
        .pin_change_req(pin_change_req),
        .transaction_done(transaction_done),
        .amount(amount),
        .card_number_input(card_number_input),
        .current_state(current_state),
        .balance(balance),
        .transaction_success(transaction_success),
        .error_code(error_code)
    );

    // Clock generation
    initial begin
        clk = 0;
        forever #5 clk = ~clk;
    end

    // Test stimulus
    initial begin
        // Initialize inputs
        rst_n = 0;
        card_inserted = 0;
        pin_input = 16'h0000;
        balance_req = 0;
        withdrawal_req = 0;
        deposit_req = 0;
        pin_change_req = 0;
        transaction_done = 0;
        amount = 16'h0000;
        card_number_input = 8'h00;

        // Reset sequence
        #20 rst_n = 1;
        
        // Test Case 1: Valid card and PIN sequence
        #20;
        card_number_input = 8'h00; // Card 0 (PIN=1234)
        card_inserted = 1;
        #20;
        
        // Enter PIN
        pin_input = 16'h1234; // Correct PIN
        #40;
        
        // Check balance
        balance_req = 1;
        #20 balance_req = 0;
        #20 transaction_done = 1;
        #20 transaction_done = 0;
        
        // Make withdrawal
        #20 withdrawal_req = 1;
        amount = 16'h0050; // Withdraw 80
        #20 withdrawal_req = 0;
        #20 transaction_done = 1;
        #20 transaction_done = 0;

        // Test Case 2: Invalid PIN sequence
        #40;
        card_number_input = 8'h01; // Card 1
        #20;
        
        pin_input = 16'h0000; // Wrong PIN
        #40;
        
        // Test timeout
        #300;
        
        // Test card removal during transaction
        card_inserted = 0;
        #20;
        
        // Test invalid card
        #20 card_number_input = 8'h02; // Inactive card
        card_inserted = 1;
        #40;

        // Test deposit
        #20 card_number_input = 8'h00;
        #20 pin_input = 16'h1234;
        #40 deposit_req = 1;
        amount = 16'h0100;
        #20 deposit_req = 0;
        #20 transaction_done = 1;
        #20 transaction_done = 0;

        // End simulation
        #100 $finish;
    end

    // Monitor outputs
    initial begin
        $monitor("Time=%0t State=%h Card=%h Pin=%h Error=%h Balance=%h Success=%b",
                 $time, current_state, card_number_input, pin_input, error_code,
                 balance, transaction_success);
                 
        // Create VCD file for waveform viewing
        $dumpfile("atm_test.vcd");
        $dumpvars(0, tb_atm_module);
    end
endmodule

verilog/atm_test.vcd
$date
	Wed Nov 20 13:09:47 2024
$end
$version
	Icarus Verilog
$end
$timescale
	1s
$end
$scope module tb_atm_module $end
$var wire 1 ! transaction_success $end
$var wire 8 " error_code [7:0] $end
$var wire 8 # current_state [7:0] $end
$var wire 16 $ balance [15:0] $end
$var reg 16 % amount [15:0] $end
$var reg 1 & balance_req $end
$var reg 1 ' card_inserted $end
$var reg 8 ( card_number_input [7:0] $end
$var reg 1 ) clk $end
$var reg 1 * deposit_req $end
$var reg 1 + pin_change_req $end
$var reg 16 , pin_input [15:0] $end
$var reg 1 - rst_n $end
$var reg 1 . transaction_done $end
$var reg 1 / withdrawal_req $end
$scope module uut $end
$var wire 16 0 amount [15:0] $end
$var wire 1 & balance_req $end
$var wire 1 ' card_inserted $end
$var wire 8 1 card_number_input [7:0] $end
$var wire 1 ) clk $end
$var wire 1 * deposit_req $end
$var wire 1 + pin_change_req $end
$var wire 16 2 pin_input [15:0] $end
$var wire 1 - rst_n $end
$var wire 1 . transaction_done $end
$var wire 1 / withdrawal_req $end
$var parameter 8 3 AMOUNT_VALID $end
$var parameter 8 4 BALANCE_ENQ $end
$var parameter 32 5 CARD_BALANCE_IDX $end
$var parameter 8 6 CARD_ERROR $end
$var parameter 8 7 CARD_INSERT $end
$var parameter 32 8 CARD_LIMIT_IDX $end
$var parameter 32 9 CARD_PIN_IDX $end
$var parameter 32 : CARD_STATUS_IDX $end
$var parameter 8 ; CARD_VALID $end
$var parameter 8 < CARD_VALIDATE $end
$var parameter 8 = DEPOSIT $end
$var parameter 8 > IDLE $end
$var parameter 8 ? INSUF_BALANCE $end
$var parameter 8 @ INVALID_CARD $end
$var parameter 8 A INVALID_PIN $end
$var parameter 8 B LIMIT_EXCEED $end
$var parameter 8 C MENU $end
$var parameter 8 D NO_ERROR $end
$var parameter 8 E PIN_CHANGE $end
$var parameter 8 F PIN_CHECK $end
$var parameter 8 G PIN_ENTRY $end
$var parameter 8 H PIN_ERROR $end
$var parameter 8 I PIN_VALID $end
$var parameter 8 J PRINT_RECEIPT $end
$var parameter 8 K WITHDRAWAL $end
$var reg 16 L balance [15:0] $end
$var reg 8 M current_card_number [7:0] $end
$var reg 8 N current_state [7:0] $end
$var reg 16 O daily_limit [15:0] $end
$var reg 8 P error_code [7:0] $end
$var reg 8 Q next_state [7:0] $end
$var reg 3 R pin_attempts [2:0] $end
$var reg 1 S pin_valid $end
$var reg 16 T stored_pin [15:0] $end
$var reg 1 ! transaction_success $end
$upscope $end
$upscope $end
$enddefinitions $end
$comment Show the parameter values. $end
$dumpall
b10001 K
b10101 J
b1000 I
b111 H
b101 G
b110 F
b10011 E
b0 D
b1001 C
b100 B
b10 A
b1 @
b11 ?
b0 >
b10010 =
b10 <
b100 ;
b10 :
b0 9
b11 8
b1 7
b11 6
b1 5
b10000 4
b10100 3
$end
#0
$dumpvars
b0 T
0S
b0 R
b0 Q
b0 P
b0 O
b0 N
b0 M
b0 L
b0 2
b0 1
b0 0
0/
0.
0-
b0 ,
0+
0*
0)
b0 (
0'
0&
b0 %
b0 $
b0 #
b0 "
0!
$end
#5
1)
#10
0)
#15
1)
#20
0)
1-
#25
1)
#30
0)
#35
1)
#40
b1 Q
0)
1'
#45
b1 #
b1 N
b10 Q
1)
#50
0)
#55
b100 Q
b10 #
b10 N
1)
#60
b100 Q
0)
b1001000110100 ,
b1001000110100 2
#65
b101 Q
b10100000000 O
b1001000110100 T
b100 #
b100 N
1)
#70
0)
#75
b101 #
b101 N
b110 Q
1)
#80
0)
#85
1S
b110 #
b110 N
b1001 Q
1)
#90
0)
#95
b1001 #
b1001 N
b1001 Q
1)
#100
b10000 Q
0)
1&
#105
b10000 #
b10000 N
1)
#110
0)
#115
b1010000010110000 $
b1010000010110000 L
1)
#120
0)
0&
#125
1)
#130
0)
#135
1)
#140
b10101 Q
0)
1.
#145
b1001 Q
1!
b10101 #
b10101 N
1)
#150
0)
#155
b1001 #
b1001 N
1)
#160
0)
0.
#165
1)
#170
0)
#175
1)
#180
b10001 Q
0)
b1010000 %
b1010000 0
1/
#185
b1001 Q
b10001 #
b10001 N
1)
#190
0)
#195
b10001 Q
b1001 #
b1001 N
1)
#200
b1001 Q
0)
0/
#205
1)
#210
0)
#215
1)
#220
0)
1.
#225
1)
#230
0)
#235
1)
#240
0)
0.
#245
1)
#250
0)
#255
1)
#260
0)
#265
1)
#270
0)
#275
1)
#280
0)
b1 (
b1 1
#285
1)
#290
0)
#295
1)
#300
0)
b0 ,
b0 2
